bitbucketserver/__init__.py
bitbucketserver/bitbucketserver.py
bitbucketserver/connection.py
bitbucketserver/resources.py
bitbucketserver/utils.py
bitbucketserver-1.2.0.dist-info/LICENSE
bitbucketserver-1.2.0.dist-info/METADATA
bitbucketserver-1.2.0.dist-info/WHEEL
bitbucketserver-1.2.0.dist-info/top_level.txt
bitbucketserver-1.2.0.dist-info/RECORD
